mos_math/__init__.py
mos_math/basics.py
mos_math/poisson.py
mos_math-0.0.4.dist-info/METADATA
mos_math-0.0.4.dist-info/WHEEL
mos_math-0.0.4.dist-info/licenses/LICENSE
mos_math-0.0.4.dist-info/RECORD
