Metadata-Version: 2.1
Name: mos_math
Version: 0.0.4
Summary: MOS (Metal Oxide Semiconductor) mathematics for C-V measurements.
Project-URL: Homepage, https://github.com/vbotka/mos-math
Project-URL: Bug Tracker, https://github.com/vbotka/mos-math/issues
Author-email: Vladimir Botka <vbotka@gmail.com>
License-File: LICENSE
Classifier: License :: OSI Approved :: BSD License
Classifier: Operating System :: OS Independent
Classifier: Programming Language :: Python :: 3
Requires-Python: >=3.7
